<?xml version="1.0" encoding="utf-8"?>
<!-- Русская локализация -->
<GameData>
	<Language_RU_RU>
<Row Tag="TXT_KEY_CIV_ASSYRIA_ADJECTIVE">
			<Text>Ассирийский</Text>
		</Row>
<Row Tag="TXT_KEY_CIV_ASSYRIA_DESC">
			<Text>Ассирийская империя</Text>
		</Row>
<Row Tag="TXT_KEY_CIV_ASSYRIA_SHORT_DESC">
			<Text>Ассирия</Text>
		</Row>
<Row Tag="TXT_KEY_CIV_BRAZIL_ADJECTIVE">
			<Text>Бразильский</Text>
		</Row>
<Row Tag="TXT_KEY_CIV_BRAZIL_DESC">
			<Text>Бразильская империя</Text>
		</Row>
<Row Tag="TXT_KEY_CIV_BRAZIL_SHORT_DESC">
			<Text>Бразилия</Text>
		</Row>
<Row Tag="TXT_KEY_CIV_INDONESIA_ADJECTIVE">
			<Text>Индонезийский</Text>
		</Row>
<Row Tag="TXT_KEY_CIV_INDONESIA_DESC">
			<Text>Индонезийская империя</Text>
		</Row>
<Row Tag="TXT_KEY_CIV_INDONESIA_SHORT_DESC">
			<Text>Индонезия</Text>
		</Row>
<Row Tag="TXT_KEY_CIV_MOROCCO_ADJECTIVE">
			<Text>Марокканский</Text>
		</Row>
<Row Tag="TXT_KEY_CIV_MOROCCO_DESC">
			<Text>Марокканская империя</Text>
		</Row>
<Row Tag="TXT_KEY_CIV_MOROCCO_SHORT_DESC">
			<Text>Марокко</Text>
		</Row>
<Row Tag="TXT_KEY_CIV_PORTUGAL_ADJECTIVE">
			<Text>Португальский</Text>
		</Row>
<Row Tag="TXT_KEY_CIV_PORTUGAL_DESC">
			<Text>Португальская империя</Text>
		</Row>
<Row Tag="TXT_KEY_CIV_PORTUGAL_SHORT_DESC">
			<Text>Португалия</Text>
		</Row>
<Row Tag="TXT_KEY_CIV_POLAND_ADJECTIVE">
			<Text>Польский</Text>
		</Row>
<Row Tag="TXT_KEY_CIV_POLAND_DESC">
			<Text>Польская империя</Text>
		</Row>
<Row Tag="TXT_KEY_CIV_POLAND_SHORT_DESC">
			<Text>Польша</Text>
		</Row>
<Row Tag="TXT_KEY_CIV_SHOSHONE_ADJECTIVE">
			<Text>Шошонский</Text>
		</Row>
<Row Tag="TXT_KEY_CIV_SHOSHONE_DESC">
			<Text>Шошоны</Text>
		</Row>
<Row Tag="TXT_KEY_CIV_SHOSHONE_SHORT_DESC">
			<Text>Шошоны</Text>
      <Plurality>2</Plurality>
		</Row>
<Row Tag="TXT_KEY_CIV_VENICE_ADJECTIVE">
			<Text>Венецианский</Text>
		</Row>
<Row Tag="TXT_KEY_CIV_VENICE_DESC">
			<Text>Республика Венеция</Text>
		</Row>
<Row Tag="TXT_KEY_CIV_VENICE_SHORT_DESC">
			<Text>Венеция</Text>
		</Row>
<Row Tag="TXT_KEY_CIV_ZULU_ADJECTIVE">
			<Text>Зулусский</Text>
		</Row>
<Row Tag="TXT_KEY_CIV_ZULU_DESC">
			<Text>Королевство Зулу</Text>
		</Row>
<Row Tag="TXT_KEY_CIV_ZULU_SHORT_DESC">
			<Text>Зулусы</Text>
      <Plurality>2</Plurality>
		</Row>
	</Language_RU_RU>
</GameData>
